cwl_utils/__init__.py
cwl_utils/__meta__.py
cwl_utils/cite_extract.py
cwl_utils/cwlNodeEngine.js
cwl_utils/cwlNodeEngineJSConsole.js
cwl_utils/cwlNodeEngineWithContext.js
cwl_utils/cwl_v1_0_expression_refactor.py
cwl_utils/cwl_v1_1_expression_refactor.py
cwl_utils/cwl_v1_2_expression_refactor.py
cwl_utils/docker_extract.py
cwl_utils/errors.py
cwl_utils/expression.py
cwl_utils/expression_refactor.py
cwl_utils/file_formats.py
cwl_utils/graph_split.py
cwl_utils/image_puller.py
cwl_utils/inputs_schema_gen.py
cwl_utils/loghandler.py
cwl_utils/normalizer.py
cwl_utils/pack.py
cwl_utils/py.typed
cwl_utils/sandboxjs.py
cwl_utils/schemadef.py
cwl_utils/singularity.py
cwl_utils/types.py
cwl_utils/utils.py
cwl_utils/parser/__init__.py
cwl_utils/parser/cwl_v1_0.py
cwl_utils/parser/cwl_v1_0_utils.py
cwl_utils/parser/cwl_v1_1.py
cwl_utils/parser/cwl_v1_1_utils.py
cwl_utils/parser/cwl_v1_2.py
cwl_utils/parser/cwl_v1_2_utils.py
cwl_utils/parser/latest.py
cwl_utils/parser/utils.py
cwl_utils/templates/workflow_input_json_schema_template.json
cwl_utils/testdata/EDAM_subset.owl
cwl_utils/testdata/bwa-mem-job.json
cwl_utils/testdata/bwa-mem-tool.cwl
cwl_utils/testdata/cond-single-source-wf-003.1.cwl
cwl_utils/testdata/cond-single-source-wf-004.1.cwl
cwl_utils/testdata/cond-single-source-wf-005.1.cwl
cwl_utils/testdata/cond-wf-003.1.cwl
cwl_utils/testdata/cond-wf-004.1.cwl
cwl_utils/testdata/cond-wf-005.1.cwl
cwl_utils/testdata/count-lines6-single-source-wf_v1_0.cwl
cwl_utils/testdata/count-lines6-single-source-wf_v1_1.cwl
cwl_utils/testdata/count-lines6-single-source-wf_v1_2.cwl
cwl_utils/testdata/count-lines6-wf_v1_0.cwl
cwl_utils/testdata/count-lines6-wf_v1_1.cwl
cwl_utils/testdata/count-lines6-wf_v1_2.cwl
cwl_utils/testdata/count-lines7-single-source-wf_v1_0.cwl
cwl_utils/testdata/count-lines7-single-source-wf_v1_1.cwl
cwl_utils/testdata/count-lines7-single-source-wf_v1_2.cwl
cwl_utils/testdata/count-lines7-wf_v1_0.cwl
cwl_utils/testdata/count-lines7-wf_v1_1.cwl
cwl_utils-0.39.dist-info/licenses/LICENSE
cwl_utils-0.39.dist-info/METADATA
cwl_utils-0.39.dist-info/WHEEL
cwl_utils-0.39.dist-info/entry_points.txt
cwl_utils-0.39.dist-info/top_level.txt
cwl_utils-0.39.dist-info/RECORD
