Metadata-Version: 2.4
Name: cwl-utils
Version: 0.39
Author-email: Common Workflow Language project contributors <common-workflow-language@googlegroups.com>
License: Apache 2.0
Project-URL: Documentation, https://cwl-utils.readthedocs.io/
Project-URL: Homepage, https://www.commonwl.org
Project-URL: Repository, https://github.com/common-workflow-language/cwl-utils
Project-URL: Issues, https://github.com/common-workflow-language/cwl-utils/issues
Project-URL: Changelog, https://github.com/common-workflow-language/cwl-utils/releases
Project-URL: Related Tools, https://www.commonwl.org/tools/
Keywords: cwl,commonwl,common-workflow-language,sciworkflows
Classifier: Development Status :: 4 - Beta
Classifier: Environment :: Console
Classifier: Intended Audience :: Developers
Classifier: License :: OSI Approved :: Apache Software License
Classifier: Operating System :: POSIX
Classifier: Operating System :: MacOS :: MacOS X
Classifier: Programming Language :: Python
Classifier: Programming Language :: Python :: 3
Classifier: Programming Language :: Python :: 3.9
Classifier: Programming Language :: Python :: 3.10
Classifier: Programming Language :: Python :: 3.11
Classifier: Programming Language :: Python :: 3.12
Classifier: Programming Language :: Python :: 3.13
Classifier: Programming Language :: Python :: 3.14
Classifier: Topic :: File Formats
Classifier: Topic :: Scientific/Engineering
Classifier: Topic :: Scientific/Engineering :: Information Analysis
Classifier: Topic :: Software Development :: Libraries
Classifier: Topic :: System :: Distributed Computing
Classifier: Typing :: Typed
Requires-Python: <3.15,>=3.9
License-File: LICENSE
Requires-Dist: cwl-upgrader>=1.2.3
Requires-Dist: packaging
Requires-Dist: rdflib
Requires-Dist: requests
Requires-Dist: schema-salad<9,>=8.8.20250205075315
Requires-Dist: ruamel.yaml<0.19,>=0.17.6
Requires-Dist: typing_extensions; python_version < "3.10"
Provides-Extra: pretty
Requires-Dist: cwlformat; extra == "pretty"
Provides-Extra: testing
Requires-Dist: pytest<9; extra == "testing"
Requires-Dist: pytest-mock; extra == "testing"
Dynamic: license-file
